{
	"tags": null,
	"angle": 1.5707963267948966,
	"innerAngle": 0,
	"exponent": 1,
	"projectionTextureLightNear": 0.000001,
	"projectionTextureLightFar": 1000,
	"projectionTextureUpDirection": {
		"_isDirty": true,
		"_x": 0,
		"_y": 1,
		"_z": 0
	},
	"diffuse": [
		1,
		1,
		1
	],
	"specular": [
		1,
		1,
		1
	],
	"falloffType": 0,
	"intensity": 1,
	"range": 1.7976931348623157e+308,
	"intensityMode": 0,
	"radius": 0.00001,
	"_renderPriority": 0,
	"shadowEnabled": true,
	"excludeWithLayerMask": 0,
	"includeOnlyWithLayerMask": 0,
	"lightmapMode": 0,
	"position": [
		10,
		10,
		10
	],
	"direction": [
		-1,
		-2,
		-1
	],
	"name": "light",
	"id": "dcc56cbb-f6c8-4de1-bbf3-3fc2421e330e",
	"state": "",
	"metadata": {
		"script": {
			"name": "src/scenes/spotlight1.ts"
		}
	},
	"uniqueId": 175,
	"type": 2,
	"animations": [],
	"ranges": [],
	"isEnabled": true,
	"parentId": null
}